keras_vision_transformer/__init__.py
keras_vision_transformer/swin_layers.py
keras_vision_transformer/transformer_layers.py
keras_vision_transformer/util_layers.py
keras_vision_transformer/utils.py
swin_transformer/AUC_LOSS.py
swin_transformer/__init__.py
swin_transformer/data_loader.py
swin_transformer/main.py
swin_transformer/model_loader.py
swin_transformer/split_data.py
tf_swin_unet-0.1.0.dist-info/LICENSE
tf_swin_unet-0.1.0.dist-info/METADATA
tf_swin_unet-0.1.0.dist-info/WHEEL
tf_swin_unet-0.1.0.dist-info/entry_points.txt
tf_swin_unet-0.1.0.dist-info/RECORD
