Metadata-Version: 2.3
Name: tf-swin-unet
Version: 0.1.0
Summary: A robust, flexible Swin UNET Transformer package for segmentation tasks.
License: MIT
Author: L-A-Sandhu
Author-email: laeeq.aslam.100@gmail.com
Requires-Python: >=3.10,<3.12
Classifier: License :: OSI Approved :: MIT License
Classifier: Programming Language :: Python :: 3
Classifier: Programming Language :: Python :: 3.10
Classifier: Programming Language :: Python :: 3.11
Requires-Dist: matplotlib (>=3.10.1,<4.0.0)
Requires-Dist: numpy (>=1.26.4,<2.0.0)
Requires-Dist: pillow (>=11.2.1,<12.0.0)
Requires-Dist: scikit-learn (>=1.6.1,<2.0.0)
Requires-Dist: scipy (>=1.15.2,<2.0.0)
Requires-Dist: tensorflow (>=2.19.0,<3.0.0)
Requires-Dist: tqdm (>=4.67.1,<5.0.0)
